{
  "device": "cuda",
  "max_epochs": 20,
  "seed_summary": [
    {
      "problem": "duffing",
      "seed": 42,
      "model": "tapinn_ao",
      "data_mse": 0.3076648712158203,
      "physics_residual": 0.0709308311343193
    },
    {
      "problem": "duffing",
      "seed": 42,
      "model": "tapinn_joint",
      "data_mse": 0.28804290294647217,
      "physics_residual": 0.06610311567783356
    },
    {
      "problem": "duffing",
      "seed": 42,
      "model": "tapinn_config",
      "data_mse": 0.3303389847278595,
      "physics_residual": 0.08453331142663956
    },
    {
      "problem": "duffing",
      "seed": 42,
      "model": "tapinn_soap",
      "data_mse": 0.25313395261764526,
      "physics_residual": 0.029223570600152016
    },
    {
      "problem": "duffing",
      "seed": 42,
      "model": "standard_pinn",
      "data_mse": 0.32469049096107483,
      "physics_residual": 0.05136459320783615
    },
    {
      "problem": "kuramoto",
      "seed": 42,
      "model": "tapinn_ao",
      "data_mse": 0.18203407526016235,
      "physics_residual": 0.9931429028511047
    },
    {
      "problem": "kuramoto",
      "seed": 42,
      "model": "tapinn_joint",
      "data_mse": 0.2393665313720703,
      "physics_residual": 0.9063820838928223
    },
    {
      "problem": "kuramoto",
      "seed": 42,
      "model": "tapinn_config",
      "data_mse": 0.2518535852432251,
      "physics_residual": 0.7341083288192749
    },
    {
      "problem": "kuramoto",
      "seed": 42,
      "model": "tapinn_soap",
      "data_mse": 0.21542906761169434,
      "physics_residual": 0.780458927154541
    },
    {
      "problem": "kuramoto",
      "seed": 42,
      "model": "standard_pinn",
      "data_mse": 1.7882106304168701,
      "physics_residual": 0.19831450283527374
    },
    {
      "problem": "lorenz",
      "seed": 42,
      "model": "tapinn_ao",
      "data_mse": 0.21995703876018524,
      "physics_residual": 0.12259950488805771
    },
    {
      "problem": "lorenz",
      "seed": 42,
      "model": "tapinn_joint",
      "data_mse": 0.19809316098690033,
      "physics_residual": 0.2133859246969223
    },
    {
      "problem": "lorenz",
      "seed": 42,
      "model": "tapinn_config",
      "data_mse": 0.17622743546962738,
      "physics_residual": 2.7817740440368652
    },
    {
      "problem": "lorenz",
      "seed": 42,
      "model": "tapinn_soap",
      "data_mse": 0.20736649632453918,
      "physics_residual": 0.21130973100662231
    },
    {
      "problem": "lorenz",
      "seed": 42,
      "model": "standard_pinn",
      "data_mse": 0.2819722890853882,
      "physics_residual": 3.278834819793701
    },
    {
      "problem": "allen_cahn",
      "seed": 42,
      "model": "tapinn_ao",
      "data_mse": 0.28320035338401794,
      "physics_residual": 0.05050808563828468
    },
    {
      "problem": "allen_cahn",
      "seed": 42,
      "model": "tapinn_joint",
      "data_mse": 0.2913525700569153,
      "physics_residual": 0.0581810288131237
    },
    {
      "problem": "allen_cahn",
      "seed": 42,
      "model": "tapinn_config",
      "data_mse": 0.28227493166923523,
      "physics_residual": 0.05459989234805107
    },
    {
      "problem": "allen_cahn",
      "seed": 42,
      "model": "tapinn_soap",
      "data_mse": 0.3721477687358856,
      "physics_residual": 0.00857256818562746
    },
    {
      "problem": "allen_cahn",
      "seed": 42,
      "model": "standard_pinn",
      "data_mse": 0.3101675808429718,
      "physics_residual": 0.02450941689312458
    },
    {
      "problem": "kuramoto_sivashinsky",
      "seed": 42,
      "model": "tapinn_ao",
      "data_mse": 0.3051258623600006,
      "physics_residual": 0.1868148297071457
    },
    {
      "problem": "kuramoto_sivashinsky",
      "seed": 42,
      "model": "tapinn_joint",
      "data_mse": 0.3005474805831909,
      "physics_residual": 0.343973308801651
    },
    {
      "problem": "kuramoto_sivashinsky",
      "seed": 42,
      "model": "tapinn_config",
      "data_mse": 0.30336055159568787,
      "physics_residual": 0.4458859860897064
    },
    {
      "problem": "kuramoto_sivashinsky",
      "seed": 42,
      "model": "tapinn_soap",
      "data_mse": 0.341663122177124,
      "physics_residual": 0.023780152201652527
    },
    {
      "problem": "kuramoto_sivashinsky",
      "seed": 42,
      "model": "standard_pinn",
      "data_mse": 0.29658955335617065,
      "physics_residual": 0.1648349016904831
    }
  ],
  "spectra": [
    {
      "problem": "duffing",
      "model": "tapinn_ao",
      "epoch": 0,
      "eigenvalues": [
        82.9464340209961,
        0.008102653548121452,
        9.71651274994656e-07,
        9.999999960041972e-13,
        9.999999960041972e-13,
        9.999999960041972e-13
      ]
    },
    {
      "problem": "duffing",
      "model": "tapinn_ao",
      "epoch": 10,
      "eigenvalues": [
        76.95100402832031,
        0.007933877408504486,
        3.3875455756060546e-06,
        1.055817847372964e-06,
        9.999999960041972e-13,
        9.999999960041972e-13
      ]
    },
    {
      "problem": "duffing",
      "model": "tapinn_ao",
      "epoch": 20,
      "eigenvalues": [
        78.31468963623047,
        0.007760743610560894,
        2.367313072682009e-06,
        2.0472506889746e-07,
        8.200175471984039e-08,
        9.999999960041972e-13
      ]
    },
    {
      "problem": "duffing",
      "model": "tapinn_joint",
      "epoch": 0,
      "eigenvalues": [
        81.5636978149414,
        0.008630272932350636,
        2.0408367618074408e-06,
        9.999999960041972e-13,
        9.999999960041972e-13,
        9.999999960041972e-13
      ]
    },
    {
      "problem": "duffing",
      "model": "tapinn_joint",
      "epoch": 10,
      "eigenvalues": [
        74.6343002319336,
        0.008017213083803654,
        9.220670108334161e-06,
        2.058587369901943e-06,
        1.03914612736844e-06,
        7.229126026686572e-07
      ]
    },
    {
      "problem": "duffing",
      "model": "tapinn_joint",
      "epoch": 20,
      "eigenvalues": [
        78.99153137207031,
        0.009032080881297588,
        1.8537626829129294e-06,
        6.093460456213506e-07,
        9.999999960041972e-13,
        9.999999960041972e-13
      ]
    },
    {
      "problem": "duffing",
      "model": "tapinn_config",
      "epoch": 0,
      "eigenvalues": [
        92.13121795654297,
        0.011186459101736546,
        3.63781828127685e-06,
        5.184856490814127e-07,
        9.999999960041972e-13,
        9.999999960041972e-13
      ]
    },
    {
      "problem": "duffing",
      "model": "tapinn_config",
      "epoch": 10,
      "eigenvalues": [
        90.05268096923828,
        0.010865602642297745,
        7.611025466758292e-06,
        1.8675874571272288e-06,
        5.4374552860281256e-08,
        9.999999960041972e-13
      ]
    },
    {
      "problem": "duffing",
      "model": "tapinn_config",
      "epoch": 20,
      "eigenvalues": [
        89.70201873779297,
        0.011494217440485954,
        1.4095859114604536e-05,
        1.3081183851681999e-06,
        9.999999960041972e-13,
        9.999999960041972e-13
      ]
    },
    {
      "problem": "duffing",
      "model": "tapinn_soap",
      "epoch": 0,
      "eigenvalues": [
        94.07085418701172,
        0.01025239285081625,
        7.857548553147353e-06,
        4.147171637214342e-07,
        9.999999960041972e-13,
        9.999999960041972e-13
      ]
    },
    {
      "problem": "duffing",
      "model": "tapinn_soap",
      "epoch": 10,
      "eigenvalues": [
        97.63816833496094,
        0.009987102821469307,
        6.2402318690146785e-06,
        2.1468963495863136e-06,
        9.999999960041972e-13,
        9.999999960041972e-13
      ]
    },
    {
      "problem": "duffing",
      "model": "tapinn_soap",
      "epoch": 20,
      "eigenvalues": [
        98.02776336669922,
        0.009614403359591961,
        5.710405730496859e-06,
        9.999999960041972e-13,
        9.999999960041972e-13,
        9.999999960041972e-13
      ]
    },
    {
      "problem": "duffing",
      "model": "standard_pinn",
      "epoch": 0,
      "eigenvalues": [
        113.5329360961914,
        0.013594569638371468,
        7.318420557567151e-06,
        2.5145156996586593e-06,
        4.842969474339043e-07,
        9.999999960041972e-13
      ]
    },
    {
      "problem": "duffing",
      "model": "standard_pinn",
      "epoch": 10,
      "eigenvalues": [
        111.6711654663086,
        0.013240196742117405,
        6.115683390817139e-06,
        5.626342272080365e-07,
        9.999999960041972e-13,
        9.999999960041972e-13
      ]
    },
    {
      "problem": "duffing",
      "model": "standard_pinn",
      "epoch": 20,
      "eigenvalues": [
        118.18818664550781,
        0.014772758819162846,
        1.0555343578744214e-05,
        3.657419028968434e-06,
        1.6455959439554135e-06,
        9.999999960041972e-13
      ]
    },
    {
      "problem": "kuramoto",
      "model": "tapinn_ao",
      "epoch": 0,
      "eigenvalues": [
        46.85284423828125,
        0.005664878990501165,
        2.611706122479518e-06,
        1.557257576223492e-07,
        9.999999960041972e-13,
        9.999999960041972e-13
      ]
    },
    {
      "problem": "kuramoto",
      "model": "tapinn_ao",
      "epoch": 10,
      "eigenvalues": [
        52.96180725097656,
        0.0058980947360396385,
        3.4245813367306255e-06,
        2.0458020344449324e-07,
        9.999999960041972e-13,
        9.999999960041972e-13
      ]
    },
    {
      "problem": "kuramoto",
      "model": "tapinn_ao",
      "epoch": 20,
      "eigenvalues": [
        72.18812561035156,
        0.006621076259762049,
        2.2456556507677305e-06,
        2.6373134787149866e-08,
        9.999999960041972e-13,
        9.999999960041972e-13
      ]
    },
    {
      "problem": "kuramoto",
      "model": "tapinn_joint",
      "epoch": 0,
      "eigenvalues": [
        61.412628173828125,
        0.006616703234612942,
        3.9297879084188025e-06,
        1.187834527627274e-06,
        9.999999960041972e-13,
        9.999999960041972e-13
      ]
    },
    {
      "problem": "kuramoto",
      "model": "tapinn_joint",
      "epoch": 10,
      "eigenvalues": [
        65.39739227294922,
        0.009229856543242931,
        4.99694988320698e-06,
        8.628844625491183e-07,
        9.999999960041972e-13,
        9.999999960041972e-13
      ]
    },
    {
      "problem": "kuramoto",
      "model": "tapinn_joint",
      "epoch": 20,
      "eigenvalues": [
        85.44664764404297,
        0.013097735121846199,
        3.2337479751731735e-06,
        2.0940628928656224e-06,
        9.999999960041972e-13,
        9.999999960041972e-13
      ]
    },
    {
      "problem": "kuramoto",
      "model": "tapinn_config",
      "epoch": 0,
      "eigenvalues": [
        64.5267333984375,
        0.007783352397382259,
        1.247216800948081e-06,
        9.999999960041972e-13,
        9.999999960041972e-13,
        9.999999960041972e-13
      ]
    },
    {
      "problem": "kuramoto",
      "model": "tapinn_config",
      "epoch": 10,
      "eigenvalues": [
        61.312686920166016,
        0.00727349566295743,
        5.403175237006508e-06,
        8.970548606157536e-07,
        9.999999960041972e-13,
        9.999999960041972e-13
      ]
    },
    {
      "problem": "kuramoto",
      "model": "tapinn_config",
      "epoch": 20,
      "eigenvalues": [
        65.79354858398438,
        0.006968578323721886,
        3.721203711393173e-06,
        2.22606422539684e-06,
        9.999999960041972e-13,
        9.999999960041972e-13
      ]
    },
    {
      "problem": "kuramoto",
      "model": "tapinn_soap",
      "epoch": 0,
      "eigenvalues": [
        70.16291809082031,
        0.006328214891254902,
        2.2513170279125916e-06,
        1.5869369462961913e-06,
        9.999999960041972e-13,
        9.999999960041972e-13
      ]
    },
    {
      "problem": "kuramoto",
      "model": "tapinn_soap",
      "epoch": 10,
      "eigenvalues": [
        72.21501922607422,
        0.006663541309535503,
        8.930949775276531e-07,
        9.999999960041972e-13,
        9.999999960041972e-13,
        9.999999960041972e-13
      ]
    },
    {
      "problem": "kuramoto",
      "model": "tapinn_soap",
      "epoch": 20,
      "eigenvalues": [
        73.32343292236328,
        0.006834329571574926,
        5.199513452680549e-06,
        3.506141013076558e-07,
        9.999999960041972e-13,
        9.999999960041972e-13
      ]
    },
    {
      "problem": "kuramoto",
      "model": "standard_pinn",
      "epoch": 0,
      "eigenvalues": [
        307.5837707519531,
        0.01106201857328415,
        2.2555777832167223e-05,
        9.999999960041972e-13,
        9.999999960041972e-13,
        9.999999960041972e-13
      ]
    },
    {
      "problem": "kuramoto",
      "model": "standard_pinn",
      "epoch": 10,
      "eigenvalues": [
        299.3969421386719,
        0.008600066415965557,
        7.428310254908865e-06,
        9.999999960041972e-13,
        9.999999960041972e-13,
        9.999999960041972e-13
      ]
    },
    {
      "problem": "kuramoto",
      "model": "standard_pinn",
      "epoch": 20,
      "eigenvalues": [
        333.730712890625,
        0.00485267722979188,
        1.5193937542790081e-05,
        1.0491457032912876e-05,
        9.999999960041972e-13,
        9.999999960041972e-13
      ]
    },
    {
      "problem": "lorenz",
      "model": "tapinn_ao",
      "epoch": 0,
      "eigenvalues": [
        79.17212677001953,
        0.0077105299569666386,
        6.380703780450858e-06,
        3.004007112394902e-06,
        3.1345174988928193e-07,
        9.999999960041972e-13
      ]
    },
    {
      "problem": "lorenz",
      "model": "tapinn_ao",
      "epoch": 10,
      "eigenvalues": [
        73.33438110351562,
        0.007251738104969263,
        5.0998978622374125e-06,
        9.999999960041972e-13,
        9.999999960041972e-13,
        9.999999960041972e-13
      ]
    },
    {
      "problem": "lorenz",
      "model": "tapinn_ao",
      "epoch": 20,
      "eigenvalues": [
        68.3111572265625,
        0.006727891508489847,
        1.5400211168525857e-06,
        9.999999960041972e-13,
        9.999999960041972e-13,
        9.999999960041972e-13
      ]
    },
    {
      "problem": "lorenz",
      "model": "tapinn_joint",
      "epoch": 0,
      "eigenvalues": [
        131.80816650390625,
        0.014569912105798721,
        5.859014891029801e-06,
        2.0536515421554213e-06,
        9.999999960041972e-13,
        9.999999960041972e-13
      ]
    },
    {
      "problem": "lorenz",
      "model": "tapinn_joint",
      "epoch": 10,
      "eigenvalues": [
        68.74205780029297,
        0.006652316078543663,
        2.9461878057190916e-06,
        1.5690562804593355e-07,
        9.999999960041972e-13,
        9.999999960041972e-13
      ]
    },
    {
      "problem": "lorenz",
      "model": "tapinn_joint",
      "epoch": 20,
      "eigenvalues": [
        67.15460205078125,
        0.006549233570694923,
        4.98222198075382e-06,
        9.713213557915878e-07,
        7.749325732220314e-07,
        9.999999960041972e-13
      ]
    },
    {
      "problem": "lorenz",
      "model": "tapinn_config",
      "epoch": 0,
      "eigenvalues": [
        75.44593048095703,
        0.00952241662889719,
        2.493777401468833e-06,
        1.523270384495845e-06,
        9.999999960041972e-13,
        9.999999960041972e-13
      ]
    },
    {
      "problem": "lorenz",
      "model": "tapinn_config",
      "epoch": 10,
      "eigenvalues": [
        69.55276489257812,
        0.007923485711216927,
        2.7333164780429797e-06,
        9.999999960041972e-13,
        9.999999960041972e-13,
        9.999999960041972e-13
      ]
    },
    {
      "problem": "lorenz",
      "model": "tapinn_config",
      "epoch": 20,
      "eigenvalues": [
        65.73829650878906,
        0.00751494849100709,
        6.493078217317816e-06,
        6.407295245480782e-07,
        9.999999960041972e-13,
        9.999999960041972e-13
      ]
    },
    {
      "problem": "lorenz",
      "model": "tapinn_soap",
      "epoch": 0,
      "eigenvalues": [
        73.8449935913086,
        0.00881494116038084,
        1.7015332787195803e-06,
        1.2380985481286189e-06,
        9.999999960041972e-13,
        9.999999960041972e-13
      ]
    },
    {
      "problem": "lorenz",
      "model": "tapinn_soap",
      "epoch": 10,
      "eigenvalues": [
        74.45343017578125,
        0.009124800562858582,
        1.954846993612591e-06,
        2.3765177559198492e-07,
        9.999999960041972e-13,
        9.999999960041972e-13
      ]
    },
    {
      "problem": "lorenz",
      "model": "tapinn_soap",
      "epoch": 20,
      "eigenvalues": [
        75.45899963378906,
        0.009095708839595318,
        7.391203325823881e-06,
        3.4278377825103234e-07,
        2.658391338172805e-07,
        9.999999960041972e-13
      ]
    },
    {
      "problem": "lorenz",
      "model": "standard_pinn",
      "epoch": 0,
      "eigenvalues": [
        494.80682373046875,
        0.00093928660498932,
        1.5492591046495363e-05,
        4.2812425817828625e-06,
        9.999999960041972e-13,
        9.999999960041972e-13
      ]
    },
    {
      "problem": "lorenz",
      "model": "standard_pinn",
      "epoch": 10,
      "eigenvalues": [
        459.14385986328125,
        0.0009199825581163168,
        8.898347005015239e-06,
        9.999999960041972e-13,
        9.999999960041972e-13,
        9.999999960041972e-13
      ]
    },
    {
      "problem": "lorenz",
      "model": "standard_pinn",
      "epoch": 20,
      "eigenvalues": [
        425.02716064453125,
        0.0008683293126523495,
        5.963260628050193e-05,
        1.426736889698077e-05,
        8.668488362673088e-07,
        9.999999960041972e-13
      ]
    },
    {
      "problem": "allen_cahn",
      "model": "tapinn_ao",
      "epoch": 0,
      "eigenvalues": [
        101.41136169433594,
        0.06374865025281906,
        1.7649297205935e-06,
        3.8479262798318814e-07,
        9.999999960041972e-13,
        9.999999960041972e-13
      ]
    },
    {
      "problem": "allen_cahn",
      "model": "tapinn_ao",
      "epoch": 10,
      "eigenvalues": [
        104.71228790283203,
        0.06855984032154083,
        6.788584414607612e-06,
        9.999999960041972e-13,
        9.999999960041972e-13,
        9.999999960041972e-13
      ]
    },
    {
      "problem": "allen_cahn",
      "model": "tapinn_ao",
      "epoch": 20,
      "eigenvalues": [
        98.03688049316406,
        0.06744644045829773,
        1.3767094060312957e-05,
        2.433557028780342e-06,
        2.634057523209776e-07,
        9.999999960041972e-13
      ]
    },
    {
      "problem": "allen_cahn",
      "model": "tapinn_joint",
      "epoch": 0,
      "eigenvalues": [
        84.2778549194336,
        0.07439576834440231,
        1.5197941138467286e-05,
        5.5020245781634e-07,
        9.999999960041972e-13,
        9.999999960041972e-13
      ]
    },
    {
      "problem": "allen_cahn",
      "model": "tapinn_joint",
      "epoch": 10,
      "eigenvalues": [
        83.66021728515625,
        0.08028285205364227,
        2.636748376971809e-06,
        1.955883590198937e-06,
        1.3131327705195872e-06,
        9.999999960041972e-13
      ]
    },
    {
      "problem": "allen_cahn",
      "model": "tapinn_joint",
      "epoch": 20,
      "eigenvalues": [
        86.27764892578125,
        0.0814732164144516,
        1.704683199932333e-05,
        1.6606280723863165e-06,
        9.999999960041972e-13,
        9.999999960041972e-13
      ]
    },
    {
      "problem": "allen_cahn",
      "model": "tapinn_config",
      "epoch": 0,
      "eigenvalues": [
        96.3836898803711,
        0.08128558099269867,
        6.180292984936386e-06,
        4.070127488375874e-06,
        1.512294375061174e-06,
        9.999999960041972e-13
      ]
    },
    {
      "problem": "allen_cahn",
      "model": "tapinn_config",
      "epoch": 10,
      "eigenvalues": [
        95.50651550292969,
        0.08323945850133896,
        1.0631522854964714e-05,
        1.170776386061334e-06,
        9.999999960041972e-13,
        9.999999960041972e-13
      ]
    },
    {
      "problem": "allen_cahn",
      "model": "tapinn_config",
      "epoch": 20,
      "eigenvalues": [
        94.20018768310547,
        0.08920984715223312,
        1.8482845916878432e-05,
        9.51554102357477e-06,
        9.999999960041972e-13,
        9.999999960041972e-13
      ]
    },
    {
      "problem": "allen_cahn",
      "model": "tapinn_soap",
      "epoch": 0,
      "eigenvalues": [
        82.62640380859375,
        0.10795821994543076,
        8.287022865260951e-06,
        4.538253961072769e-06,
        9.999999960041972e-13,
        9.999999960041972e-13
      ]
    },
    {
      "problem": "allen_cahn",
      "model": "tapinn_soap",
      "epoch": 10,
      "eigenvalues": [
        86.63926696777344,
        0.11528171598911285,
        1.4877326066198293e-05,
        5.176283593755215e-06,
        2.080618742184015e-06,
        9.999999960041972e-13
      ]
    },
    {
      "problem": "allen_cahn",
      "model": "tapinn_soap",
      "epoch": 20,
      "eigenvalues": [
        89.89906311035156,
        0.12165765464305878,
        2.2808791982242838e-05,
        6.643625056312885e-06,
        1.0932977829725132e-06,
        9.999999960041972e-13
      ]
    },
    {
      "problem": "allen_cahn",
      "model": "standard_pinn",
      "epoch": 0,
      "eigenvalues": [
        169.13973999023438,
        0.1180814877152443,
        8.603094101999886e-06,
        5.160923137736972e-06,
        9.999999960041972e-13,
        9.999999960041972e-13
      ]
    },
    {
      "problem": "allen_cahn",
      "model": "standard_pinn",
      "epoch": 10,
      "eigenvalues": [
        165.152099609375,
        0.11929182708263397,
        7.307066880457569e-06,
        6.410482910723658e-06,
        9.999999960041972e-13,
        9.999999960041972e-13
      ]
    },
    {
      "problem": "allen_cahn",
      "model": "standard_pinn",
      "epoch": 20,
      "eigenvalues": [
        152.81349182128906,
        0.10604575276374817,
        8.356444595847279e-06,
        1.446628630219493e-06,
        9.999999960041972e-13,
        9.999999960041972e-13
      ]
    },
    {
      "problem": "kuramoto_sivashinsky",
      "model": "tapinn_ao",
      "epoch": 0,
      "eigenvalues": [
        97.55077362060547,
        0.06490419805049896,
        7.079283477651188e-06,
        2.7948560727963923e-06,
        9.999999960041972e-13,
        9.999999960041972e-13
      ]
    },
    {
      "problem": "kuramoto_sivashinsky",
      "model": "tapinn_ao",
      "epoch": 10,
      "eigenvalues": [
        95.94972229003906,
        0.06368644535541534,
        5.398151643021265e-06,
        2.960814299513004e-06,
        9.251056667380908e-07,
        9.999999960041972e-13
      ]
    },
    {
      "problem": "kuramoto_sivashinsky",
      "model": "tapinn_ao",
      "epoch": 20,
      "eigenvalues": [
        91.7108154296875,
        0.06101135537028313,
        8.777359653322492e-06,
        3.4418926588841714e-06,
        9.999999960041972e-13,
        9.999999960041972e-13
      ]
    },
    {
      "problem": "kuramoto_sivashinsky",
      "model": "tapinn_joint",
      "epoch": 0,
      "eigenvalues": [
        84.72377014160156,
        0.07341231405735016,
        1.0980827028106432e-05,
        1.3844564819009975e-06,
        9.999999960041972e-13,
        9.999999960041972e-13
      ]
    },
    {
      "problem": "kuramoto_sivashinsky",
      "model": "tapinn_joint",
      "epoch": 10,
      "eigenvalues": [
        86.67894744873047,
        0.07118739187717438,
        6.321481123450212e-06,
        3.255154751968803e-06,
        9.999999960041972e-13,
        9.999999960041972e-13
      ]
    },
    {
      "problem": "kuramoto_sivashinsky",
      "model": "tapinn_joint",
      "epoch": 20,
      "eigenvalues": [
        83.96790313720703,
        0.06951770931482315,
        7.353361070272513e-06,
        4.296874976716936e-06,
        9.999999960041972e-13,
        9.999999960041972e-13
      ]
    },
    {
      "problem": "kuramoto_sivashinsky",
      "model": "tapinn_config",
      "epoch": 0,
      "eigenvalues": [
        92.40238189697266,
        0.0847388356924057,
        9.979960850614589e-06,
        5.273117039905628e-06,
        9.168031738227e-07,
        9.999999960041972e-13
      ]
    },
    {
      "problem": "kuramoto_sivashinsky",
      "model": "tapinn_config",
      "epoch": 10,
      "eigenvalues": [
        93.7088851928711,
        0.08309049904346466,
        7.154135801101802e-06,
        9.999999960041972e-13,
        9.999999960041972e-13,
        9.999999960041972e-13
      ]
    },
    {
      "problem": "kuramoto_sivashinsky",
      "model": "tapinn_config",
      "epoch": 20,
      "eigenvalues": [
        90.22685241699219,
        0.08355444669723511,
        9.208108167513274e-06,
        9.93004732663394e-07,
        9.999999960041972e-13,
        9.999999960041972e-13
      ]
    },
    {
      "problem": "kuramoto_sivashinsky",
      "model": "tapinn_soap",
      "epoch": 0,
      "eigenvalues": [
        80.80826568603516,
        0.10707315057516098,
        1.4893932529957965e-05,
        1.9628482732514385e-06,
        9.999999960041972e-13,
        9.999999960041972e-13
      ]
    },
    {
      "problem": "kuramoto_sivashinsky",
      "model": "tapinn_soap",
      "epoch": 10,
      "eigenvalues": [
        78.50648498535156,
        0.10305464267730713,
        9.004005733004306e-06,
        1.7302310197919724e-06,
        9.999999960041972e-13,
        9.999999960041972e-13
      ]
    },
    {
      "problem": "kuramoto_sivashinsky",
      "model": "tapinn_soap",
      "epoch": 20,
      "eigenvalues": [
        78.60929107666016,
        0.10029038786888123,
        1.024724497256102e-05,
        3.8528742152266204e-06,
        1.3070766726741567e-06,
        9.999999960041972e-13
      ]
    },
    {
      "problem": "kuramoto_sivashinsky",
      "model": "standard_pinn",
      "epoch": 0,
      "eigenvalues": [
        169.13973999023438,
        0.1180814877152443,
        8.603094101999886e-06,
        5.160923137736972e-06,
        9.999999960041972e-13,
        9.999999960041972e-13
      ]
    },
    {
      "problem": "kuramoto_sivashinsky",
      "model": "standard_pinn",
      "epoch": 10,
      "eigenvalues": [
        161.8922119140625,
        0.11521084606647491,
        1.703045745671261e-05,
        3.7390309444162995e-06,
        9.999999960041972e-13,
        9.999999960041972e-13
      ]
    },
    {
      "problem": "kuramoto_sivashinsky",
      "model": "standard_pinn",
      "epoch": 20,
      "eigenvalues": [
        151.2640838623047,
        0.10894440859556198,
        9.46336513152346e-06,
        7.046678092592629e-06,
        9.999999960041972e-13,
        9.999999960041972e-13
      ]
    }
  ],
  "conditioning": [
    {
      "problem": "duffing",
      "model": "tapinn_ao",
      "epoch": 0,
      "condition_number": 862883.375,
      "lipschitz": 0.023608196526765823
    },
    {
      "problem": "duffing",
      "model": "tapinn_ao",
      "epoch": 10,
      "condition_number": 1024190.25,
      "lipschitz": 0.015777798369526863
    },
    {
      "problem": "duffing",
      "model": "tapinn_ao",
      "epoch": 20,
      "condition_number": 1139525.25,
      "lipschitz": 0.017787424847483635
    },
    {
      "problem": "duffing",
      "model": "tapinn_joint",
      "epoch": 0,
      "condition_number": 1044984.5,
      "lipschitz": 0.012363526970148087
    },
    {
      "problem": "duffing",
      "model": "tapinn_joint",
      "epoch": 10,
      "condition_number": 1192151.5,
      "lipschitz": 0.016386495903134346
    },
    {
      "problem": "duffing",
      "model": "tapinn_joint",
      "epoch": 20,
      "condition_number": 1788621.625,
      "lipschitz": 0.018096769228577614
    },
    {
      "problem": "duffing",
      "model": "tapinn_config",
      "epoch": 0,
      "condition_number": 1289904.625,
      "lipschitz": 0.019733576104044914
    },
    {
      "problem": "duffing",
      "model": "tapinn_config",
      "epoch": 10,
      "condition_number": 1050424.875,
      "lipschitz": 0.01963157393038273
    },
    {
      "problem": "duffing",
      "model": "tapinn_config",
      "epoch": 20,
      "condition_number": 1118822.0,
      "lipschitz": 0.024130089208483696
    },
    {
      "problem": "duffing",
      "model": "tapinn_soap",
      "epoch": 0,
      "condition_number": 1029107.3125,
      "lipschitz": 0.016048509627580643
    },
    {
      "problem": "duffing",
      "model": "tapinn_soap",
      "epoch": 10,
      "condition_number": 899038.8125,
      "lipschitz": 0.018041089177131653
    },
    {
      "problem": "duffing",
      "model": "tapinn_soap",
      "epoch": 20,
      "condition_number": 1621728.5,
      "lipschitz": 0.01808742620050907
    },
    {
      "problem": "duffing",
      "model": "standard_pinn",
      "epoch": 0,
      "condition_number": 26306884.0,
      "lipschitz": 0.0
    },
    {
      "problem": "duffing",
      "model": "standard_pinn",
      "epoch": 10,
      "condition_number": 24510246.0,
      "lipschitz": 0.0
    },
    {
      "problem": "duffing",
      "model": "standard_pinn",
      "epoch": 20,
      "condition_number": 26456974.0,
      "lipschitz": 0.0
    },
    {
      "problem": "kuramoto",
      "model": "tapinn_ao",
      "epoch": 0,
      "condition_number": 1067659.625,
      "lipschitz": 0.07017574459314346
    },
    {
      "problem": "kuramoto",
      "model": "tapinn_ao",
      "epoch": 10,
      "condition_number": 999783.75,
      "lipschitz": 0.05842738598585129
    },
    {
      "problem": "kuramoto",
      "model": "tapinn_ao",
      "epoch": 20,
      "condition_number": 839252.3125,
      "lipschitz": 0.06014350801706314
    },
    {
      "problem": "kuramoto",
      "model": "tapinn_joint",
      "epoch": 0,
      "condition_number": 1465600.875,
      "lipschitz": 0.04522135853767395
    },
    {
      "problem": "kuramoto",
      "model": "tapinn_joint",
      "epoch": 10,
      "condition_number": 1879130.875,
      "lipschitz": 0.0630175843834877
    },
    {
      "problem": "kuramoto",
      "model": "tapinn_joint",
      "epoch": 20,
      "condition_number": 667376.5,
      "lipschitz": 0.11796335875988007
    },
    {
      "problem": "kuramoto",
      "model": "tapinn_config",
      "epoch": 0,
      "condition_number": 1409097.0,
      "lipschitz": 0.043827325105667114
    },
    {
      "problem": "kuramoto",
      "model": "tapinn_config",
      "epoch": 10,
      "condition_number": 1661567.125,
      "lipschitz": 0.04247627407312393
    },
    {
      "problem": "kuramoto",
      "model": "tapinn_config",
      "epoch": 20,
      "condition_number": 976983.8125,
      "lipschitz": 0.04501261189579964
    },
    {
      "problem": "kuramoto",
      "model": "tapinn_soap",
      "epoch": 0,
      "condition_number": 1588165.0,
      "lipschitz": 0.054434362798929214
    },
    {
      "problem": "kuramoto",
      "model": "tapinn_soap",
      "epoch": 10,
      "condition_number": 2091764.5,
      "lipschitz": 0.044857800006866455
    },
    {
      "problem": "kuramoto",
      "model": "tapinn_soap",
      "epoch": 20,
      "condition_number": 1847252.0,
      "lipschitz": 0.045579347759485245
    },
    {
      "problem": "kuramoto",
      "model": "standard_pinn",
      "epoch": 0,
      "condition_number": 22416336.0,
      "lipschitz": 0.0
    },
    {
      "problem": "kuramoto",
      "model": "standard_pinn",
      "epoch": 10,
      "condition_number": 26992614.0,
      "lipschitz": 0.0
    },
    {
      "problem": "kuramoto",
      "model": "standard_pinn",
      "epoch": 20,
      "condition_number": 27445396.0,
      "lipschitz": 0.0
    },
    {
      "problem": "lorenz",
      "model": "tapinn_ao",
      "epoch": 0,
      "condition_number": 114799.0390625,
      "lipschitz": 0.017530083656311035
    },
    {
      "problem": "lorenz",
      "model": "tapinn_ao",
      "epoch": 10,
      "condition_number": 133064.453125,
      "lipschitz": 0.013149822130799294
    },
    {
      "problem": "lorenz",
      "model": "tapinn_ao",
      "epoch": 20,
      "condition_number": 208893.171875,
      "lipschitz": 0.013457904569804668
    },
    {
      "problem": "lorenz",
      "model": "tapinn_joint",
      "epoch": 0,
      "condition_number": 146822.28125,
      "lipschitz": 0.014202434569597244
    },
    {
      "problem": "lorenz",
      "model": "tapinn_joint",
      "epoch": 10,
      "condition_number": 317759.21875,
      "lipschitz": 0.009468589909374714
    },
    {
      "problem": "lorenz",
      "model": "tapinn_joint",
      "epoch": 20,
      "condition_number": 288009.0,
      "lipschitz": 0.009198534302413464
    },
    {
      "problem": "lorenz",
      "model": "tapinn_config",
      "epoch": 0,
      "condition_number": 138588.90625,
      "lipschitz": 0.010620217770338058
    },
    {
      "problem": "lorenz",
      "model": "tapinn_config",
      "epoch": 10,
      "condition_number": 277771.71875,
      "lipschitz": 0.01134708896279335
    },
    {
      "problem": "lorenz",
      "model": "tapinn_config",
      "epoch": 20,
      "condition_number": 242315.046875,
      "lipschitz": 0.011455744504928589
    },
    {
      "problem": "lorenz",
      "model": "tapinn_soap",
      "epoch": 0,
      "condition_number": 218537.546875,
      "lipschitz": 0.014373533427715302
    },
    {
      "problem": "lorenz",
      "model": "tapinn_soap",
      "epoch": 10,
      "condition_number": 304068.71875,
      "lipschitz": 0.015549544245004654
    },
    {
      "problem": "lorenz",
      "model": "tapinn_soap",
      "epoch": 20,
      "condition_number": 462413.53125,
      "lipschitz": 0.012489985674619675
    },
    {
      "problem": "lorenz",
      "model": "standard_pinn",
      "epoch": 0,
      "condition_number": 17402422.0,
      "lipschitz": 0.0
    },
    {
      "problem": "lorenz",
      "model": "standard_pinn",
      "epoch": 10,
      "condition_number": 19839796.0,
      "lipschitz": 0.0
    },
    {
      "problem": "lorenz",
      "model": "standard_pinn",
      "epoch": 20,
      "condition_number": 17580786.0,
      "lipschitz": 0.0
    },
    {
      "problem": "allen_cahn",
      "model": "tapinn_ao",
      "epoch": 0,
      "condition_number": 455777.125,
      "lipschitz": 0.09000567346811295
    },
    {
      "problem": "allen_cahn",
      "model": "tapinn_ao",
      "epoch": 10,
      "condition_number": 408867.25,
      "lipschitz": 0.08602269738912582
    },
    {
      "problem": "allen_cahn",
      "model": "tapinn_ao",
      "epoch": 20,
      "condition_number": 702206.9375,
      "lipschitz": 0.07895313203334808
    },
    {
      "problem": "allen_cahn",
      "model": "tapinn_joint",
      "epoch": 0,
      "condition_number": 321312.9375,
      "lipschitz": 0.09098775684833527
    },
    {
      "problem": "allen_cahn",
      "model": "tapinn_joint",
      "epoch": 10,
      "condition_number": 665473.8125,
      "lipschitz": 0.06141029670834541
    },
    {
      "problem": "allen_cahn",
      "model": "tapinn_joint",
      "epoch": 20,
      "condition_number": 546785.125,
      "lipschitz": 0.059221263974905014
    },
    {
      "problem": "allen_cahn",
      "model": "tapinn_config",
      "epoch": 0,
      "condition_number": 625116.25,
      "lipschitz": 0.10668117552995682
    },
    {
      "problem": "allen_cahn",
      "model": "tapinn_config",
      "epoch": 10,
      "condition_number": 499673.03125,
      "lipschitz": 0.10467618703842163
    },
    {
      "problem": "allen_cahn",
      "model": "tapinn_config",
      "epoch": 20,
      "condition_number": 630439.25,
      "lipschitz": 0.09081224352121353
    },
    {
      "problem": "allen_cahn",
      "model": "tapinn_soap",
      "epoch": 0,
      "condition_number": 588137.8125,
      "lipschitz": 0.0872427225112915
    },
    {
      "problem": "allen_cahn",
      "model": "tapinn_soap",
      "epoch": 10,
      "condition_number": 437921.1875,
      "lipschitz": 0.12976723909378052
    },
    {
      "problem": "allen_cahn",
      "model": "tapinn_soap",
      "epoch": 20,
      "condition_number": 555331.5,
      "lipschitz": 0.143010675907135
    },
    {
      "problem": "allen_cahn",
      "model": "standard_pinn",
      "epoch": 0,
      "condition_number": 25716936.0,
      "lipschitz": 0.0
    },
    {
      "problem": "allen_cahn",
      "model": "standard_pinn",
      "epoch": 10,
      "condition_number": 26550676.0,
      "lipschitz": 0.0
    },
    {
      "problem": "allen_cahn",
      "model": "standard_pinn",
      "epoch": 20,
      "condition_number": 24391146.0,
      "lipschitz": 0.0
    },
    {
      "problem": "kuramoto_sivashinsky",
      "model": "tapinn_ao",
      "epoch": 0,
      "condition_number": 1302804.875,
      "lipschitz": 0.08140118420124054
    },
    {
      "problem": "kuramoto_sivashinsky",
      "model": "tapinn_ao",
      "epoch": 10,
      "condition_number": 1023559.25,
      "lipschitz": 0.08031459897756577
    },
    {
      "problem": "kuramoto_sivashinsky",
      "model": "tapinn_ao",
      "epoch": 20,
      "condition_number": 1706307.5,
      "lipschitz": 0.07406079024076462
    },
    {
      "problem": "kuramoto_sivashinsky",
      "model": "tapinn_joint",
      "epoch": 0,
      "condition_number": 1437182.875,
      "lipschitz": 0.11458352208137512
    },
    {
      "problem": "kuramoto_sivashinsky",
      "model": "tapinn_joint",
      "epoch": 10,
      "condition_number": 1425928.75,
      "lipschitz": 0.11174840480089188
    },
    {
      "problem": "kuramoto_sivashinsky",
      "model": "tapinn_joint",
      "epoch": 20,
      "condition_number": 1131448.875,
      "lipschitz": 0.1113000214099884
    },
    {
      "problem": "kuramoto_sivashinsky",
      "model": "tapinn_config",
      "epoch": 0,
      "condition_number": 3050480.25,
      "lipschitz": 0.09363078325986862
    },
    {
      "problem": "kuramoto_sivashinsky",
      "model": "tapinn_config",
      "epoch": 10,
      "condition_number": 1490350.75,
      "lipschitz": 0.10033335536718369
    },
    {
      "problem": "kuramoto_sivashinsky",
      "model": "tapinn_config",
      "epoch": 20,
      "condition_number": 3246751.5,
      "lipschitz": 0.1038891151547432
    },
    {
      "problem": "kuramoto_sivashinsky",
      "model": "tapinn_soap",
      "epoch": 0,
      "condition_number": 2295131.0,
      "lipschitz": 0.12016057223081589
    },
    {
      "problem": "kuramoto_sivashinsky",
      "model": "tapinn_soap",
      "epoch": 10,
      "condition_number": 1847367.375,
      "lipschitz": 0.13431257009506226
    },
    {
      "problem": "kuramoto_sivashinsky",
      "model": "tapinn_soap",
      "epoch": 20,
      "condition_number": 2001332.125,
      "lipschitz": 0.1549796760082245
    },
    {
      "problem": "kuramoto_sivashinsky",
      "model": "standard_pinn",
      "epoch": 0,
      "condition_number": 25716936.0,
      "lipschitz": 0.0
    },
    {
      "problem": "kuramoto_sivashinsky",
      "model": "standard_pinn",
      "epoch": 10,
      "condition_number": 25303442.0,
      "lipschitz": 0.0
    },
    {
      "problem": "kuramoto_sivashinsky",
      "model": "standard_pinn",
      "epoch": 20,
      "condition_number": 22801552.0,
      "lipschitz": 0.0
    }
  ]
}